{
	"$schema": "http://schema.management.azure.com/schemas/2015-01-01/deploymentTemplate.json#",
	"contentVersion": "1.0.0.0",
	"parameters": {
		"factoryName": {
			"type": "string",
			"metadata": "Data Factory name",
			"defaultValue": "azure-data-factory4all"
		},
		"InputBlob_connectionString": {
			"type": "secureString",
			"metadata": "Secure string for 'connectionString' of 'InputBlob'"
		},
		"OutputSQL_connectionString": {
			"type": "secureString",
			"metadata": "Secure string for 'connectionString' of 'OutputSQL'"
		}
	},
	"variables": {
		"factoryId": "[concat('Microsoft.DataFactory/factories/', parameters('factoryName'))]"
	},
	"resources": [
		{
			"name": "[concat(parameters('factoryName'), '/Blob to SQL')]",
			"type": "Microsoft.DataFactory/factories/pipelines",
			"apiVersion": "2018-06-01",
			"properties": {
				"activities": [
					{
						"name": "Sales CSV to SQL",
						"type": "Copy",
						"dependsOn": [],
						"policy": {
							"timeout": "0.12:00:00",
							"retry": 0,
							"retryIntervalInSeconds": 30,
							"secureOutput": false,
							"secureInput": false
						},
						"userProperties": [],
						"typeProperties": {
							"source": {
								"type": "DelimitedTextSource",
								"storeSettings": {
									"type": "AzureBlobStorageReadSettings",
									"recursive": true,
									"enablePartitionDiscovery": false
								},
								"formatSettings": {
									"type": "DelimitedTextReadSettings"
								}
							},
							"sink": {
								"type": "AzureSqlSink",
								"writeBehavior": "insert",
								"sqlWriterUseTableLock": false
							},
							"enableStaging": false,
							"translator": {
								"type": "TabularTranslator",
								"typeConversion": true,
								"typeConversionSettings": {
									"allowDataTruncation": true,
									"treatBooleanAsNumber": false
								}
							}
						},
						"inputs": [
							{
								"referenceName": "salescsv",
								"type": "DatasetReference",
								"parameters": {}
							}
						],
						"outputs": [
							{
								"referenceName": "salessql",
								"type": "DatasetReference",
								"parameters": {}
							}
						]
					}
				],
				"policy": {
					"elapsedTimeMetric": {},
					"cancelAfter": {}
				},
				"annotations": []
			},
			"dependsOn": [
				"[concat(variables('factoryId'), '/datasets/salescsv')]",
				"[concat(variables('factoryId'), '/datasets/salessql')]"
			]
		},
		{
			"name": "[concat(parameters('factoryName'), '/salescsv')]",
			"type": "Microsoft.DataFactory/factories/datasets",
			"apiVersion": "2018-06-01",
			"properties": {
				"linkedServiceName": {
					"referenceName": "InputBlob",
					"type": "LinkedServiceReference"
				},
				"annotations": [],
				"type": "DelimitedText",
				"typeProperties": {
					"location": {
						"type": "AzureBlobStorageLocation",
						"fileName": "sales_data_sample.csv",
						"container": "input"
					},
					"columnDelimiter": ";",
					"escapeChar": "\\",
					"firstRowAsHeader": true,
					"quoteChar": "\""
				},
				"schema": [
					{
						"name": "ORDER_UNIQUE_ID",
						"type": "String"
					},
					{
						"name": "ORDERNUMBER",
						"type": "String"
					},
					{
						"name": "QUANTITYORDERED",
						"type": "String"
					},
					{
						"name": "PRICEEACH",
						"type": "String"
					},
					{
						"name": "ORDERLINENUMBER",
						"type": "String"
					},
					{
						"name": "SALES",
						"type": "String"
					},
					{
						"name": "ORDERDATE",
						"type": "String"
					},
					{
						"name": "STATUS",
						"type": "String"
					},
					{
						"name": "QTR_ID",
						"type": "String"
					},
					{
						"name": "MONTH_ID",
						"type": "String"
					},
					{
						"name": "YEAR_ID",
						"type": "String"
					},
					{
						"name": "PRODUCTLINE",
						"type": "String"
					},
					{
						"name": "MSRP",
						"type": "String"
					},
					{
						"name": "PRODUCTCODE",
						"type": "String"
					},
					{
						"name": "CUSTOMERNAME",
						"type": "String"
					},
					{
						"name": "PHONE",
						"type": "String"
					},
					{
						"name": "ADDRESSLINE1",
						"type": "String"
					},
					{
						"name": "ADDRESSLINE2",
						"type": "String"
					},
					{
						"name": "CITY",
						"type": "String"
					},
					{
						"name": "STATE",
						"type": "String"
					},
					{
						"name": "POSTALCODE",
						"type": "String"
					},
					{
						"name": "COUNTRY",
						"type": "String"
					},
					{
						"name": "TERRITORY",
						"type": "String"
					},
					{
						"name": "CONTACTLASTNAME",
						"type": "String"
					},
					{
						"name": "CONTACTFIRSTNAME",
						"type": "String"
					},
					{
						"name": "DEALSIZE",
						"type": "String"
					}
				]
			},
			"dependsOn": [
				"[concat(variables('factoryId'), '/linkedServices/InputBlob')]"
			]
		},
		{
			"name": "[concat(parameters('factoryName'), '/salessql')]",
			"type": "Microsoft.DataFactory/factories/datasets",
			"apiVersion": "2018-06-01",
			"properties": {
				"linkedServiceName": {
					"referenceName": "OutputSQL",
					"type": "LinkedServiceReference"
				},
				"annotations": [],
				"type": "AzureSqlTable",
				"schema": [
					{
						"name": "ORDER_UNIQUE_ID",
						"type": "int",
						"precision": 10
					},
					{
						"name": "ORDERNUMBER",
						"type": "int",
						"precision": 10
					},
					{
						"name": "QUANTITYORDERED",
						"type": "int",
						"precision": 10
					},
					{
						"name": "PRICEEACH",
						"type": "varchar"
					},
					{
						"name": "ORDERLINENUMBER",
						"type": "int",
						"precision": 10
					},
					{
						"name": "SALES",
						"type": "decimal",
						"precision": 7,
						"scale": 2
					},
					{
						"name": "ORDERDATE",
						"type": "varchar"
					},
					{
						"name": "STATUS",
						"type": "varchar"
					},
					{
						"name": "QTR_ID",
						"type": "int",
						"precision": 10
					},
					{
						"name": "MONTH_ID",
						"type": "int",
						"precision": 10
					},
					{
						"name": "YEAR_ID",
						"type": "int",
						"precision": 10
					},
					{
						"name": "PRODUCTLINE",
						"type": "varchar"
					},
					{
						"name": "MSRP",
						"type": "int",
						"precision": 10
					},
					{
						"name": "PRODUCTCODE",
						"type": "varchar"
					},
					{
						"name": "CUSTOMERNAME",
						"type": "varchar"
					},
					{
						"name": "PHONE",
						"type": "varchar"
					},
					{
						"name": "ADDRESSLINE1",
						"type": "varchar"
					},
					{
						"name": "ADDRESSLINE2",
						"type": "varchar"
					},
					{
						"name": "CITY",
						"type": "varchar"
					},
					{
						"name": "STATE",
						"type": "varchar"
					},
					{
						"name": "POSTALCODE",
						"type": "varchar"
					},
					{
						"name": "COUNTRY",
						"type": "varchar"
					},
					{
						"name": "TERRITORY",
						"type": "varchar"
					},
					{
						"name": "CONTACTLASTNAME",
						"type": "varchar"
					},
					{
						"name": "CONTACTFIRSTNAME",
						"type": "varchar"
					},
					{
						"name": "DEALSIZE",
						"type": "varchar"
					}
				],
				"typeProperties": {
					"schema": "dbo",
					"table": "Sales"
				}
			},
			"dependsOn": [
				"[concat(variables('factoryId'), '/linkedServices/OutputSQL')]"
			]
		},
		{
			"name": "[concat(parameters('factoryName'), '/InputBlob')]",
			"type": "Microsoft.DataFactory/factories/linkedServices",
			"apiVersion": "2018-06-01",
			"properties": {
				"annotations": [],
				"type": "AzureBlobStorage",
				"typeProperties": {
					"connectionString": "[parameters('InputBlob_connectionString')]"
				}
			},
			"dependsOn": []
		},
		{
			"name": "[concat(parameters('factoryName'), '/OutputSQL')]",
			"type": "Microsoft.DataFactory/factories/linkedServices",
			"apiVersion": "2018-06-01",
			"properties": {
				"annotations": [],
				"type": "AzureSqlDatabase",
				"typeProperties": {
					"connectionString": "[parameters('OutputSQL_connectionString')]"
				}
			},
			"dependsOn": []
		}
	]
}